{
    "en": [
      "■ Squamous Cell Carcinoma (SCC):",
      "● Epidemiology and General Information:",
      "-> Most common type of skin cancer in India.",
      "-> Commonly seen on sun-exposed areas such as the head, neck, and hands.",
      "-> Typically presents as a firm, red nodule or a flat lesion with a scaly, crusted surface.",
      "● Risk Factors:",
      "-> Prolonged UV exposure (especially UVB)",
      "-> Chronic skin inflammation",
      "-> Human papillomavirus (HPV) infection",
      "-> Arsenic exposure in drinking water (particularly common in rural areas of India)"
    ],
    "as": [
      "■ স্কোৱামাছ চেল কাৰ্চিনোমা (SCC):",
      "● মহামাৰীৰ বিজ্ঞান আৰু সামান্য তথ্য:",
      "-> ভাৰতত ছালৰ কেঞ্চাৰৰ আটাইতকৈ সাধাৰণ প্ৰকাৰ।",
      "-> সাধাৰণতে মূৰ, গলা আৰু হাতৰ দৰে সূৰ্যৰ আলোকিত এলেকাত দেখা যায়।",
      "-> সাধাৰণতে এটা দৃঢ়, ৰঙা গুটি বা এটা সমতল ক্ষত ৰূপে পোহৰিত হয় য'ত এটা চেঁচা, ক্ৰাস্টেড পৃষ্ঠ থাকে।",
      "● ঝুঁকিৰ কাৰক:",
      "-> দীঘলীয়া UV পৰ্দা (বিশেষকৈ UVB)",
      "-> দীঘলীয়া ছালৰ সোঁহাৰণ",
      "-> মানব প্যাপিলোমাভাইৰাছ (HPV) সংক্রমণ",
      "-> পানীয় জলে আর্সেনিকৰ সংস্পৰ্শ (বিশেষকৈ ভাৰতৰ গ্ৰাম্য অঞ্চলত সাধাৰণ)"
    ],
    "awa": [
      "■ स्क्वामस सेल कार्सिनोमा (एससीसी):",
      "● महामारी विज्ञान और सामान्य जानकारी:",
      "-> भारत में त्वचा के कैंसर का सबसे आम प्रकार।",
      "-> आमतौर पर सिर, गर्दन और हाथों जैसे सूर्य-उजागर क्षेत्रों पर देखा जाता है।",
      "-> आमतौर पर एक ठोस, लाल गाँठ या एक सपाट घाव के रूप में प्रस्तुत होता है जिसमें एक पपड़ीदार, क्रस्टेड सतह होती है।",
      "● जोखिम कारक:",
      "-> लंबी अवधि के यूवी संपर्क (विशेषकर यूवीबी)",
      "-> पुरानी त्वचा की सूजन",
      "-> मानव पैपिलोमावायरस (एचपीवी) संक्रमण",
      "-> पीने के पानी में आर्सेनिक का संपर्क (विशेष रूप से भारत के ग्रामीण क्षेत्रों में आम)"
    ],
    "bn": [
      "■ স্কোয়ামাস সেল কার্সিনোমা (এসসিসি):",
      "● মহামারি বিদ্যা এবং সাধারণ তথ্য:",
      "-> ভারতের সবচেয়ে সাধারণ ধরনের ত্বকের ক্যান্সার।",
      "-> সাধারণত মাথা, গলা এবং হাতের মত সূর্যালোকিত এলাকায় দেখা যায়।",
      "-> সাধারণত একটি কঠিন, লাল গিঁট বা একটি সমতল ক্ষত হিসাবে উপস্থিত হয় যার একটি আঁশযুক্ত, পাঁকানো পৃষ্ঠ থাকে।",
      "● ঝুঁকির কারণ:",
      "-> দীর্ঘকালীন UV রশ্মির সংস্পর্শ (বিশেষ করে UVB)",
      "-> দীর্ঘস্থায়ী ত্বকের প্রদাহ",
      "-> মানব প্যাপিলোমাভাইরাস (HPV) সংক্রমণ",
      "-> পানীয় জলে আর্সেনিকের সংস্পর্শ (বিশেষ করে ভারতের গ্রামীণ এলাকায় সাধারণ)"
    ],
    "bho": [
      "■ स्क्वामस सेल कार्सिनोमा (एससीसी):",
      "● महामारी विज्ञान और सामान्य जानकारी:",
      "-> भारत में त्वचा के कैंसर का सबसे आम प्रकार।",
      "-> आमतौर पर सिर, गर्दन और हाथों जैसे सूर्य-उजागर क्षेत्रों पर देखा जाता है।",
      "-> आमतौर पर एक ठोस, लाल गाँठ या एक सपाट घाव के रूप में प्रस्तुत होता है जिसमें एक पपड़ीदार, क्रस्टेड सतह होती है।",
      "● जोखिम कारक:",
      "-> लंबी अवधि के यूवी संपर्क (विशेषकर यूवीबी)",
      "-> पुरानी त्वचा की सूजन",
      "-> मानव पैपिलोमावायरस (एचपीवी) संक्रमण",
      "-> पीने के पानी में आर्सेनिक का संपर्क (विशेष रूप से भारत के ग्रामीण क्षेत्रों में आम)"
    ],
    "chg": [
      "■ स्क्वामस सेल कार्सिनोमा (एससीसी):",
      "● महामारी विज्ञान और सामान्य जानकारी:",
      "-> भारत में त्वचा के कैंसर का सबसे आम प्रकार।",
      "-> आमतौर पर सिर, गर्दन और हाथों जैसे सूर्य-उजागर क्षेत्रों पर देखा जाता है।",
      "-> आमतौर पर एक ठोस, लाल गाँठ या एक सपाट घाव के रूप में प्रस्तुत होता है जिसमें एक पपड़ीदार, क्रस्टेड सतह होती है।",
      "● जोखिम कारक:",
      "-> लंबी अवधि के यूवी संपर्क (विशेषकर यूवीबी)",
      "-> पुरानी त्वचा की सूजन",
      "-> मानव पैपिलोमावायरस (एचपीवी) संक्रमण",
      "-> पीने के पानी में आर्सेनिक का संपर्क (विशेष रूप से भारत के ग्रामीण क्षेत्रों में आम)"
    ],
    "doi": [
      "■ स्क्वामस सेल कार्सिनोमा (एससीसी):",
      "● महामारी विज्ञान और सामान्य जानकारी:",
      "-> भारत में त्वचा के कैंसर का सबसे आम प्रकार।",
      "-> आमतौर पर सिर, गर्दन और हाथों जैसे सूर्य-उजागर क्षेत्रों पर देखा जाता है।",
      "-> आमतौर पर एक ठोस, लाल गाँठ या एक सपाट घाव के रूप में प्रस्तुत होता है जिसमें एक पपड़ीदार, क्रस्टेड सतह होती है।",
      "● जोखिम कारक:",
      "-> लंबी अवधि के यूवी संपर्क (विशेषकर यूवीबी)",
      "-> पुरानी त्वचा की सूजन",
      "-> मानव पैपिलोमावायरस (एचपीवी) संक्रमण",
      "-> पीने के पानी में आर्सेनिक का संपर्क (विशेष रूप से भारत के ग्रामीण क्षेत्रों में आम)"
    ],
    "gu": [
      "■ સ્ક્વામસ સેલ કાર્સિનોમા (એસસીસી):",
      "● મહામારી વિજ્ઞાન અને સામાન્ય માહિતી:",
      "-> ભારતમાં ત્વચા કૅન્સરનો સૌથી સામાન્ય પ્રકાર.",
      "-> સામાન્ય રીતે મસ્તક, ગળું અને હાથ જેવા સૂર્યપ્રકાશિત વિસ્તારોમાં જોવા મળે છે.",
      "-> સામાન્ય રીતે એક મજબૂત, લાલ ગાંઠ અથવા એક સપાટ ઘાવ તરીકે રજૂ થાય છે જેમાં એક છાલદાર, પાંખોળી વટ હોય છે.",
      "● જોખમના કારણો:",
      "-> લાંબી સમયગાળા માટે UV ઉગમ (ખાસ કરીને UVB)",
      "-> દીર્ઘકાળીન ત્વચાની સોજા",
      "-> માનવ પેપિલોમાવાયરસ (HPV) સંક્રમણ",
      "-> પીવાના પાણીમાં આર્સેનિકના સંપર્ક (ખાસ કરીને ભારતના ગ્રામ્ય વિસ્તારોમાં સામાન્ય)"
    ],
    "hne": [
      "■ स्क्वामस सेल कार्सिनोमा (एससीसी):",
      "● महामारी विज्ञान और सामान्य जानकारी:",
      "-> भारत में त्वचा के कैंसर का सबसे आम प्रकार।",
      "-> आमतौर पर सिर, गर्दन और हाथों जैसे सूर्य-उजागर क्षेत्रों पर देखा जाता है।",
      "-> आमतौर पर एक ठोस, लाल गाँठ या एक सपाट घाव के रूप में प्रस्तुत होता है जिसमें एक पपड़ीदार, क्रस्टेड सतह होती है।",
      "● जोखिम कारक:",
      "-> लंबी अवधि के यूवी संपर्क (विशेषकर यूवीबी)",
      "-> पुरानी त्वचा की सूजन",
      "-> मानव पैपिलोमावायरस (एचपीवी) संक्रमण",
      "-> पीने के पानी में आर्सेनिक का संपर्क (विशेष रूप से भारत के ग्रामीण क्षेत्रों में आम)"
    ],
    "hi": [
      "■ स्क्वैमस सेल कार्सिनोमा (एससीसी):",
      "● महामारी विज्ञान और सामान्य जानकारी:",
      "-> भारत में त्वचा के कैंसर का सबसे आम प्रकार।",
      "-> आमतौर पर सिर, गर्दन और हाथों जैसे सूर्य-उजागर क्षेत्रों पर देखा जाता है।",
      "-> आमतौर पर एक ठोस, लाल गाँठ या एक सपाट घाव के रूप में प्रस्तुत होता है जिसमें एक पपड़ीदार, क्रस्टेड सतह होती है।",
      "● जोखिम कारक:",
      "-> लंबी अवधि के यूवी संपर्क (विशेषकर यूवीबी)",
      "-> पुरानी त्वचा की सूजन",
      "-> मानव पैपिलोमावायरस (एचपीवी) संक्रमण",
      "-> पीने के पानी में आर्सेनिक का संपर्क (विशेष रूप से भारत के ग्रामीण क्षेत्रों में आम)"
    ],
    "kn": [
      "■ ಸ್ಕ್ವಾಮಸ್ ಸೆಲ್ ಕಾರ್ಸಿನೋಮಾ (ಎಸ್‌ಸಿ‌ಸಿ):",
      "● ಮಹಾಮಾರಿ ಶಾಸ್ತ್ರ ಮತ್ತು ಸಾಮಾನ್ಯ ಮಾಹಿತಿ:",
      "-> ಭಾರತದಲ್ಲಿ ಚರ್ಮ ಕ್ಯಾನ್ಸರ್‌ನ ಅತ್ಯಂತ ಸಾಮಾನ್ಯ ಪ್ರಕಾರ.",
      "-> ಸಾಮಾನ್ಯವಾಗಿ ತಲೆ, ಕುತ್ತಿಗೆ ಮತ್ತು ಕೈಗಳು ಮುಂತಾದ ಸೂರ್ಯಪ್ರಕಾಶಿತ ಪ್ರದೇಶಗಳಲ್ಲಿ ಕಂಡುಬರುತ್ತದೆ.",
      "-> ಸಾಮಾನ್ಯವಾಗಿ ದೃಢವಾದ, ಕೆಂಪು ಗುಳ್ಳೆ ಅಥವಾ ತೆಳುವಾದ ಹಾನಿಯ ರೂಪದಲ್ಲಿ ಪ್ರಸ್ತುತವಾಗುತ್ತದೆ, ಇದರಲ್ಲಿ ಒಂದು ಸ್ಕೇಲಿ, ಕ್ರಸ್ಟೆಡ್ ಮೇಲ್ಮೈಯುಂಟು.",
      "● ಅಪಾಯ ಕಾರಣಗಳು:",
      "-> ದೀರ್ಘಕಾಲದ ಯುವಿ ಬೆಳಕು (ವಿಶೇಷವಾಗಿ ಯುವಿ ಬಿ)",
      "-> ದೀರ್ಘಕಾಲದ ಚರ್ಮದ ರೋಗ",
      "-> ಮಾನವ ಪ್ಯಾಪಿಲೋಮಾವೈರಸ್ (ಎಚ್ಪಿವಿ) ಸೋಂಕು",
      "-> ಕುಡಿಯುವ ನೀರಿನಲ್ಲಿ ಆರ್ಸೆನಿಕ್ ಸಂಪರ್ಕ (ಭಾರತದ ಗ್ರಾಮಾಂತರ ಪ್ರದೇಶಗಳಲ್ಲಿ ಸಾಮಾನ್ಯವಾಗಿ ಕಂಡುಬರುವುದರೊಂದಿಗೆ)"
    ],
    "ks": [
      "■ स्क्वामस सेल कार्सिनोमा (एससीसी):",
      "● महामारी विज्ञान और सामान्य जानकारी:",
      "-> भारत में त्वचा के कैंसर का सबसे आम प्रकार।",
      "-> आमतौर पर सिर, गर्दन और हाथों जैसे सूर्य-उजागर क्षेत्रों पर देखा जाता है।",
      "-> आमतौर पर एक ठोस, लाल गाँठ या एक सपाट घाव के रूप में प्रस्तुत होता है जिसमें एक पपड़ीदार, क्रस्टेड सतह होती है।",
      "● जोखिम कारक:",
      "-> लंबी अवधि के यूवी संपर्क (विशेषकर यूवीबी)",
      "-> पुरानी त्वचा की सूजन",
      "-> मानव पैपिलोमावायरस (एचपीवी) संक्रमण",
      "-> पीने के पानी में आर्सेनिक का संपर्क (विशेष रूप से भारत के ग्रामीण क्षेत्रों में आम)"
    ],
    "kok": [
      "■ स्क्वामस सेल कार्सिनोमा (एससीसी):",
      "● महामारी विज्ञान और सामान्य जानकारी:",
      "-> भारत में त्वचा के कैंसर का सबसे आम प्रकार।",
      "-> आमतौर पर सिर, गर्दन और हाथों जैसे सूर्य-उजागर क्षेत्रों पर देखा जाता है।",
      "-> आमतौर पर एक ठोस, लाल गाँठ या एक सपाट घाव के रूप में प्रस्तुत होता है जिसमें एक पपड़ीदार, क्रस्टेड सतह होती है।",
      "● जोखिम कारक:",
      "-> लंबी अवधि के यूवी संपर्क (विशेषकर यूवीबी)",
      "-> पुरानी त्वचा की सूजन",
      "-> मानव पैपिलोमावायरस (एचपीवी) संक्रमण",
      "-> पीने के पानी में आर्सेनिक का संपर्क (विशेष रूप से भारत के ग्रामीण क्षेत्रों में आम)"
    ],
    "mai": [
      "■ स्क्वामस सेल कार्सिनोमा (एससीसी):",
      "● महामारी विज्ञान और सामान्य जानकारी:",
      "-> भारत में त्वचा के कैंसर का सबसे आम प्रकार।",
      "-> आमतौर पर सिर, गर्दन और हाथों जैसे सूर्य-उजागर क्षेत्रों पर देखा जाता है।",
      "-> आमतौर पर एक ठोस, लाल गाँठ या एक सपाट घाव के रूप में प्रस्तुत होता है जिसमें एक पपड़ीदार, क्रस्टेड सतह होती है।",
      "● जोखिम कारक:",
      "-> लंबी अवधि के यूवी संपर्क (विशेषकर यूवीबी)",
      "-> पुरानी त्वचा की सूजन",
      "-> मानव पैपिलोमावायरस (एचपीवी) संक्रमण",
      "-> पीने के पानी में आर्सेनिक का संपर्क (विशेष रूप से भारत के ग्रामीण क्षेत्रों में आम)"
    ],
    "ml": [
      "■ സ്ക്വാമസ് സെൽ കാർസിനോമ (എസ്എസ്എസ്സ്):",
      "● മഹാമാരി ശാസ്ത്രം మరియు പൊതുവായ വിവരങ്ങൾ:",
      "-> ഇന്ത്യയിലെ ഏറ്റവും സാധാരണ തരം ചർമ്മ കാൻസർ.",
      "-> സാധാരണയായി തല, കഴുത്ത്, കൈകളിലെ സൂര്യപ്രകാശം ലഭിക്കുന്ന പ്രദേശങ്ങളിൽ കാണപ്പെടുന്നു.",
      "-> സാധാരണയായി ഒരു ദൃഢമായ, ചുവന്ന ഗോലി അല്ലെങ്കിൽ ഒരു ലൊകേഷൻ ഒരു സ്കാലി, ക്രസ്റ്റെഡ് ഉപരിതലം ഉള്ളത് കാണപ്പെടുന്നു.",
      "● അപകടസാധ്യതകൾ:",
      "-> ദീർഘകാല യു.വി. (വിശേഷിച്ച് UVB)",
      "-> ദീർഘകാല ചർമ്മ വ്യാധി",
      "-> മനുഷ്യ പാപ്പിലോമാവൈറസ് (HPV) ഇൻഫെക്ഷൻ",
      "-> കുടിവെള്ളത്തിൽ ആഴ്സെനിക് സമ്പർക്കം (ഇന്ത്യയുടെ ഗ്രാമപ്രദേശങ്ങളിൽ പൊതുവായിരിക്കുന്നു)"
    ],
    "mni": [
      "■ স্কোয়ামাস সেল কার্সিনোমা (এসসিসি):",
      "● মহামারি বিদ্যা এবং সাধারণ তথ্য:",
      "-> ভারতের সবচেয়ে সাধারণ ধরনের ত্বকের ক্যান্সার।",
      "-> সাধারণত মাথা, গলা এবং হাতের মত সূর্যালোকিত এলাকায় দেখা যায়।",
      "-> সাধারণত একটি কঠিন, লাল গিঁট বা একটি সমতল ক্ষত হিসাবে উপস্থিত হয় যার একটি আঁশযুক্ত, পাঁকানো পৃষ্ঠ থাকে।",
      "● ঝুঁকির কারণ:",
      "-> দীর্ঘকালীন UV রশ্মির সংস্পর্শ (বিশেষ করে UVB)",
      "-> দীর্ঘস্থায়ী ত্বকের প্রদাহ",
      "-> মানব প্যাপিলোমাভাইরাস (HPV) সংক্রমণ",
      "-> পানীয় জলে আর্সেনিকের সংস্পর্শ (বিশেষ করে ভারতের গ্রামীণ এলাকায় সাধারণ)"
    ],
    "mr": [
      "■ स्क्वामस सेल कार्सिनोमा (एससीसी):",
      "● महामारी विज्ञान और सामान्य जानकारी:",
      "-> भारत में त्वचा के कैंसर का सबसे आम प्रकार।",
      "-> आमतौर पर सिर, गर्दन और हाथों जैसे सूर्य-उजागर क्षेत्रों पर देखा जाता है।",
      "-> आमतौर पर एक ठोस, लाल गाँठ या एक सपाट घाव के रूप में प्रस्तुत होता है जिसमें एक पपड़ीदार, क्रस्टेड सतह होती है।",
      "● जोखिम कारक:",
      "-> लंबी अवधि के यूवी संपर्क (विशेषकर यूवीबी)",
      "-> पुरानी त्वचा की सूजन",
      "-> मानव पैपिलोमावायरस (एचपीवी) संक्रमण",
      "-> पीने के पानी में आर्सेनिक का संपर्क (विशेष रूप से भारत के ग्रामीण क्षेत्रों में आम)"
    ],
    "ne": [
      "■ स्क्वामस सेल कार्सिनोमा (एससीसी):",
      "● महामारी विज्ञान और सामान्य जानकारी:",
      "-> भारत में त्वचा के कैंसर का सबसे आम प्रकार।",
      "-> आमतौर पर सिर, गर्दन और हाथों जैसे सूर्य-उजागर क्षेत्रों पर देखा जाता है।",
      "-> आमतौर पर एक ठोस, लाल गाँठ या एक सपाट घाव के रूप में प्रस्तुत होता है जिसमें एक पपड़ीदार, क्रस्टेड सतह होती है।",
      "● जोखिम कारक:",
      "-> लंबी अवधि के यूवी संपर्क (विशेषकर यूवीबी)",
      "-> पुरानी त्वचा की सूजन",
      "-> मानव पैपिलोमावायरस (एचपीवी) संक्रमण",
      "-> पीने के पानी में आर्सेनिक का संपर्क (विशेष रूप से भारत के ग्रामीण क्षेत्रों में आम)"
    ],
    "or": [
      "■ স্কোয়ামাস সেল কার্সিনোমা (এসসিসি):",
      "● মহামারি বিদ্যা এবং সাধারণ তথ্য:",
      "-> ভারতের সবচেয়ে সাধারণ ধরনের ত্বকের ক্যান্সার।",
      "-> সাধারণত মাথা, গলা এবং হাতের মত সূর্যালোকিত এলাকায় দেখা যায়।",
      "-> সাধারণত একটি কঠিন, লাল গিঁট বা একটি সমতল ক্ষত হিসাবে উপস্থিত হয় যার একটি আঁশযুক্ত, পাঁকানো পৃষ্ঠ থাকে।",
      "● ঝুঁকির কারণ:",
      "-> দীর্ঘকালীন UV রশ্মির সংস্পর্শ (বিশেষ করে UVB)",
      "-> দীর্ঘস্থায়ী ত্বকের প্রদাহ",
      "-> মানব প্যাপিলোমাভাইরাস (HPV) সংক্রমণ",
      "-> পানীয় জলে আর্সেনিকের সংস্পর্শ (বিশেষ করে ভারতের গ্রামীণ এলাকায় সাধারণ)"
    ],
    "pa": [
      "■ स्क्वामस सेल कार्सिनोमा (एससीसी):",
      "● महामारी विज्ञान और सामान्य जानकारी:",
      "-> भारत में त्वचा के कैंसर का सबसे आम प्रकार।",
      "-> आमतौर पर सिर, गर्दन और हाथों जैसे सूर्य-उजागर क्षेत्रों पर देखा जाता है।",
      "-> आमतौर पर एक ठोस, लाल गाँठ या एक सपाट घाव के रूप में प्रस्तुत होता है जिसमें एक पपड़ीदार, क्रस्टेड सतह होती है।",
      "● जोखिम कारक:",
      "-> लंबी अवधि के यूवी संपर्क (विशेषकर यूवीबी)",
      "-> पुरानी त्वचा की सूजन",
      "-> मानव पैपिलोमावायरस (एचपीवी) संक्रमण",
      "-> पीने के पानी में आर्सेनिक का संपर्क (विशेष रूप से भारत के ग्रामीण क्षेत्रों में आम)"
    ],
    "sa": [
      "■ स्क्वामस सेल कार्सिनोमा (एससीसी):",
      "● महामारी विज्ञान और सामान्य जानकारी:",
      "-> भारत में त्वचा के कैंसर का सबसे आम प्रकार।",
      "-> आमतौर पर सिर, गर्दन और हाथों जैसे सूर्य-उजागर क्षेत्रों पर देखा जाता है।",
      "-> आमतौर पर एक ठोस, लाल गाँठ या एक सपाट घाव के रूप में प्रस्तुत होता है जिसमें एक पपड़ीदार, क्रस्टेड सतह होती है।",
      "● जोखिम कारक:",
      "-> लंबी अवधि के यूवी संपर्क (विशेषकर यूवीबी)",
      "-> पुरानी त्वचा की सूजन",
      "-> मानव पैपिलोमावायरस (एचपीवी) संक्रमण",
      "-> पीने के पानी में आर्सेनिक का संपर्क (विशेष रूप से भारत के ग्रामीण क्षेत्रों में आम)"
    ],
    "sat": [
      "■ स्क्वामस सेल कार्सिनोमा (एससीसी):",
      "● महामारी विज्ञान और सामान्य जानकारी:",
      "-> भारत में त्वचा के कैंसर का सबसे आम प्रकार।",
      "-> आमतौर पर सिर, गर्दन और हाथों जैसे सूर्य-उजागर क्षेत्रों पर देखा जाता है।",
      "-> आमतौर पर एक ठोस, लाल गाँठ या एक सपाट घाव के रूप में प्रस्तुत होता है जिसमें एक पपड़ीदार, क्रस्टेड सतह होती है।",
      "● जोखिम कारक:",
      "-> लंबी अवधि के यूवी संपर्क (विशेषकर यूवीबी)",
      "-> पुरानी त्वचा की सूजन",
      "-> मानव पैपिलोमावायरस (एचपीवी) संक्रमण",
      "-> पीने के पानी में आर्सेनिक का संपर्क (विशेष रूप से भारत के ग्रामीण क्षेत्रों में आम)"
    ],
    "sd": [
      "■ स्क्वामस सेल कार्सिनोमा (एससीसी):",
      "● महामारी विज्ञान और सामान्य जानकारी:",
      "-> भारत में त्वचा के कैंसर का सबसे आम प्रकार।",
      "-> आमतौर पर सिर, गर्दन और हाथों जैसे सूर्य-उजागर क्षेत्रों पर देखा जाता है।",
      "-> आमतौर पर एक ठोस, लाल गाँठ या एक सपाट घाव के रूप में प्रस्तुत होता है जिसमें एक पपड़ीदार, क्रस्टेड सतह होती है।",
      "● जोखिम कारक:",
      "-> लंबी अवधि के यूवी संपर्क (विशेषकर यूवीबी)",
      "-> पुरानी त्वचा की सूजन",
      "-> मानव पैपिलोमावायरस (एचपीवी) संक्रमण",
      "-> पीने के पानी में आर्सेनिक का संपर्क (विशेष रूप से भारत के ग्रामीण क्षेत्रों में आम)"
    ],
    "ta": [
      "■ ஸ்குவாமஸ் செல்கள் கார்சினோமா (எஸ்சி):",
      "● தொற்று பரவல் மற்றும் பொது தகவல்கள்:",
      "-> இந்தியாவில் சருமப் புற்றுநோயின் மிகவும் பொதுவான வகை.",
      "-> பொதுவாக தலை, கழுத்து மற்றும் கைகளின் போன்ற சூரிய வெளிப்படுத்தப்பட்ட பகுதிகளில் காணப்படுகிறது.",
      "-> பொதுவாக ஒரு திடமான, சிவப்பு முடிச்சு அல்லது ஒரு சிமிழ்மான, அகற்றப்பட்ட மேற்பரப்புடன் ஒரு சமமான காயம்.",
      "● ஆபத்து காரணிகள்:",
      "-> நீண்டகால UV வெளிப்பாடு (விசேஷமாக UVB)",
      "-> நீண்டகால சரும சினப்பு",
      "-> மனித பாப்பிலோமாவைரஸ் (HPV) தொற்று",
      "-> குடிநீரில் ஆர்செனிக் தொடர்பு (விசேஷமாக இந்தியாவின் கிராமப்புறங்களில் பொதுவாக)"
    ],
    "te": [
      "■ స్క్వామస్ సెల్ కార్సినోమా (ఎస్ఎస్సీ):",
      "● మహమ్మారి విజ్ఞానం మరియు సాధారణ సమాచారం:",
      "-> భారతదేశంలో చర్మ కేన్సర్ యొక్క అత్యంత సాధారణ రకం.",
      "-> సాధారణంగా తల, మెడ మరియు చేతుల వంటి సూర్యకాంతి వెలువడే ప్రాంతాల్లో కనిపిస్తుంది.",
      "-> సాధారణంగా ఒక బలమైన, ఎర్ర గుళిక లేదా ఒక ఫ్లాట్ గాయం వలె ప్రదర్శిస్తుంది, ఇది ఒక స్కేలీ, క్రస్టెడ్ ఉపరితలం కలిగి ఉంటుంది.",
      "● ప్రమాద కారకాలు:",
      "-> దీర్ఘకాలం యూవీ వెలుపల (ప్రత్యేకించి యూవీబి)",
      "-> దీర్ఘకాలిక చర్మ కంటినేషన్",
      "-> మానవ పాపిలోమావైరస్ (హెచ్పివి) ఇన్ఫెక్షన్",
      "-> త్రాగు నీటిలో ఆర్సెనిక్ వెలుపల (ప్రత్యేకించి భారతదేశం యొక్క గ్రామీణ ప్రాంతాలలో సాధారణంగా)"
    ],
    "ur": [
      "■ اسکوا مس سیل کارسینوما (ایس سی سی):",
      "● وبائی امراض اور عمومی معلومات:",
      "-> ہندوستان میں جلد کے کینسر کی سب سے عام قسم۔",
      "-> عام طور پر سر، گردن اور ہاتھوں جیسے سورج کی روشنی میں نظر آتی ہے۔",
      "-> عام طور پر ایک مضبوط، سرخ گانٹھ یا ایک فلیٹ زخم کے طور پر ظاہر ہوتا ہے جس کی سطح پر ایک پرت دار، کھردری سطح ہوتی ہے۔",
      "● خطرے کے عوامل:",
      "-> طویل مدتی یو وی کی نمائش (خاص طور پر یو وی بی)",
      "-> دائمی جلد کی سوزش",
      "-> انسانی پیپیلوما وائرس (ایچ پی وی) کا انفیکشن",
      "-> پینے کے پانی میں سنکھیا کی نمائش (خاص طور پر بھارت کے دیہی علاقوں میں عام)"
    ]
  }
  